zoom_api_helper/__init__.py
zoom_api_helper/__version__.py
zoom_api_helper/constants.py
zoom_api_helper/log.py
zoom_api_helper/models.py
zoom_api_helper/oauth.py
zoom_api_helper/utils.py
zoom_api_helper/v2.py
zoom_api_helper-0.1.1.dist-info/LICENSE
zoom_api_helper-0.1.1.dist-info/METADATA
zoom_api_helper-0.1.1.dist-info/WHEEL
zoom_api_helper-0.1.1.dist-info/top_level.txt
zoom_api_helper-0.1.1.dist-info/RECORD
