Metadata-Version: 2.1
Name: zoom-api-helper
Version: 0.1.1
Summary: Utilities to interact with the Zoom API v2
Home-page: https://github.com/rnag/zoom-api-helper
Author: Ritvik Nag
Author-email: rv.kvetch@gmail.com
License: MIT
Project-URL: Documentation, https://zoom-api-helper.readthedocs.io
Project-URL: Source, https://github.com/rnag/zoom-api-helper
Keywords: zoom-api-helper,zoom,api,zoom-api,api-v2
Platform: UNKNOWN
Classifier: Development Status :: 5 - Production/Stable
Classifier: Intended Audience :: Developers
Classifier: License :: OSI Approved :: MIT License
Classifier: Natural Language :: English
Classifier: Programming Language :: Python :: 3 :: Only
Classifier: Programming Language :: Python :: 3
Classifier: Programming Language :: Python :: 3.7
Classifier: Programming Language :: Python :: 3.8
Classifier: Programming Language :: Python :: 3.9
Classifier: Programming Language :: Python :: 3.10
Classifier: Programming Language :: Python
Requires-Dist: requests
Requires-Dist: backports.cached-property (~=1.0.2) ; python_version == "3.7"
Requires-Dist: typing-extensions ; python_version == "3.7"
Provides-Extra: all
Requires-Dist: sheet2dict ; extra == 'all'
Provides-Extra: excel
Requires-Dist: sheet2dict ; extra == 'excel'
